cenroctest/__init__.py
cenroctest/cenroctest.py
cenroctest-0.0.12.dist-info/METADATA
cenroctest-0.0.12.dist-info/WHEEL
cenroctest-0.0.12.dist-info/top_level.txt
cenroctest-0.0.12.dist-info/RECORD
