Metadata-Version: 2.1
Name: cenroctest
Version: 0.0.12
Summary: Calculation of censored ROC curve
Author: Yury Moskaltsov
Author-email: yury-m@hotmail.com
Keywords: python,cenROC,survival
Classifier: Programming Language :: Python :: 3
Classifier: License :: OSI Approved :: MIT License
Classifier: Operating System :: OS Independent
Requires-Python: >=3.6
Requires-Dist: numpy
Requires-Dist: pandas
Requires-Dist: matplotlib
Requires-Dist: scipy
Requires-Dist: statsmodels
